pypargen/__init__.py
pypargen/base/__init__.py
pypargen/base/grammar.py
pypargen/base/lexer.py
pypargen/base/parser.py
pypargen/base/rule.py
pypargen/base/token.py
pypargen/grm/__init__.py
pypargen/grm/grammar.py
pypargen/grm/parser.py
pypargen/lexer/__init__.py
pypargen/lexer/fsm.py
pypargen/lexer/lexer.py
pypargen/lexer/pyre.py
pypargen/lexer/re.py
pypargen/lr1/__init__.py
pypargen/lr1/grammar.py
pypargen/lr1/parser.py
pypargen-0.3.0.dist-info/COPYING
pypargen-0.3.0.dist-info/WHEEL
pypargen-0.3.0.dist-info/METADATA
pypargen-0.3.0.dist-info/RECORD
